crazyhusk/__init__.py
crazyhusk/__main__.py
crazyhusk/__version__.py
crazyhusk/build.py
crazyhusk/cli.py
crazyhusk/code.py
crazyhusk/config.py
crazyhusk/engine.py
crazyhusk/importsettings.py
crazyhusk/logs.py
crazyhusk/module.py
crazyhusk/plugin.py
crazyhusk/project.py
crazyhusk/render.py
crazyhusk/reports.py
crazyhusk/linux/__init__.py
crazyhusk/mac/__init__.py
crazyhusk/windows/__init__.py
crazyhusk/windows/engine.py
crazyhusk-0.1.5.dist-info/LICENSE
crazyhusk-0.1.5.dist-info/METADATA
crazyhusk-0.1.5.dist-info/WHEEL
crazyhusk-0.1.5.dist-info/entry_points.txt
crazyhusk-0.1.5.dist-info/top_level.txt
crazyhusk-0.1.5.dist-info/RECORD
