Metadata-Version: 2.1
Name: crazyhusk
Version: 0.1.5
Summary: Dependency-free Python object wrappers for working with Unreal Engine
Home-page: https://github.com/nhaines-pro/python-crazyhusk.git
Author: Nick Haines
Author-email: nhaines.pro@gmail.com
License: MIT
Platform: UNKNOWN
License-File: LICENSE
Requires-Dist: importlib-metadata ; python_version < "3.8"
Provides-Extra: dev
Requires-Dist: pytest ; extra == 'dev'
Requires-Dist: isort ; extra == 'dev'
Requires-Dist: black ; extra == 'dev'
Requires-Dist: mypy ; extra == 'dev'
Requires-Dist: pycodestyle ; extra == 'dev'
Requires-Dist: pydocstyle ; extra == 'dev'
Requires-Dist: pre-commit ; extra == 'dev'
Requires-Dist: pre-commit-hooks ; extra == 'dev'
Provides-Extra: test
Requires-Dist: pytest ; extra == 'test'
